
{
    
    
    
    
    
    
    
    
        
        
        
    
    "articles": [{"date":"2025-04-07","image":"","imageAlt":"","link":"http://localhost:1313/posts/building-my-website-in-hugo/","summary":"\u003cp\u003eI always wanted a website/blog to write articles about what I like, so today I decided to make one!\u003c/p\u003e\n\u003cp\u003eAfter buying a domain and setting up the server I had just to decide what to write the website with.\u003c/p\u003e\n\u003ch2 id=\"hugo\"\u003eHugo\u003c/h2\u003e\n\u003cp\u003e\u003cimg src=\"https://gohugo.io/images/hugo-logo-wide.svg\" alt=\"hugo-logo\"\u003e\u003c/p\u003e\n\u003cp\u003eAs a tech stack I wanted something simple and easy to mantain,\n\u003ca href=\"https://gohugo.io/\"\u003eHugo\u003c/a\u003e makes everything so easy and painless that it is too good to be true.\u003c/p\u003e\n\u003cp\u003eJust install it and then write in the terminal\u003c/p\u003e","tags":["hosting","website"],"title":"Building my website in Hugo"}],
    "test": "Building my website in Hugo   ",
    "page": "1",
    "next": ""
}

